{
  "citation": "",
  "description": "",
  "features": {
    "id": {
      "dtype": "int64",
      "_type": "Value"
    },
    "domain": {
      "dtype": "string",
      "_type": "Value"
    },
    "qa_pairs": [
      {
        "answer": {
          "dtype": "string",
          "_type": "Value"
        },
        "question": {
          "dtype": "string",
          "_type": "Value"
        }
      }
    ],
    "num_pairs": {
      "dtype": "int64",
      "_type": "Value"
    }
  },
  "homepage": "",
  "license": ""
}